[
  {
    "title": "Graphic Design Essentials Canva",
    "issuer": "Canva",
    "image": "/assets/certificates/canva_gde.jpg",
    "link": "https://www.canva.com/design-school/certification-award/e1104e36-eb9e-4aa7-88db-561c24bdf125",
    "issueDate": "31st December 2024"
  },
  {
    "title": "Github Foundations",
    "issuer": "Github",
    "image": "/assets/certificates/github.jpg",
    "link": "https://www.credly.com/badges/d1247516-3577-40c1-a7fe-d1fda8f0a1af",
    "issueDate": "31st December 2024"
  },
  {
    "title": "Machine Learning & Data Science Expert",
    "issuer": "Charusat University",
    "image": "/assets/certificates/ml.jpg",
    "link": "https://drive.google.com/file/d/1dXVau4YcFQ1SJoZY5Z-RQHIVxjPFXTjb/view",
    "issueDate": "23rd November 2024"
  },
  {
    "title": "Idea Show 3.0",
    "issuer": "Charusat University",
    "image": "/assets/certificates/ideashow.jpg",
    "link": "https://drive.google.com/file/d/1izDTJdsRU6mpiF_5qxLzKt7Bnnwd1urx/view",
    "issueDate": "8th October 2024"
  },
  {
    "title": "Canva Essentials",
    "issuer": "Canva",
    "image": "/assets/certificates/canva_ess.jpg",
    "link": "hhttps://www.canva.com/design-school/certification-award/cc43637a-56c5-4ce2-b008-c008e6776a69",
    "issueDate": "8th October 2024"
  },
  {
    "title": "Postman API Fundamentals Student Expert",
    "issuer": "Postman",
    "image": "/assets/certificates/postman.jpg",
    "link": "https://badgr.com/public/assertions/-By_ZEt6QdWw11VGUi-LAA",
    "issueDate": "7th October 2024"
  },
  {
    "title": "Google Play Store Listing",
    "issuer": "Google",
    "image": "/assets/certificates/playstore.jpg",
    "link": "https://www.credential.net/cbb993b9-7d35-4282-bf5b-d27663bbd8a7",
    "issueDate": "6th July 2024",
    "expiryDate": "6th July 2027"
  },
  {
    "title": "Android App Developement",
    "issuer": "Internshala",
    "image": "/assets/certificates/android_app.jpg",
    "link": "https://trainings.internshala.com/view_certificate/9k5pbn5c4ib/eag8ql50h36/",
    "issueDate": "8th March 2024"
  },
  {
    "title": "Foundation of Digital Marketing & E-Commerce",
    "issuer": "Coursera · Google",
    "image": "/assets/certificates/coursera.jpg",
    "link": "https://www.coursera.org/account/accomplishments/verify/KZ8ZVBY8N6YV",
    "issueDate": "25th February 2024"
    },
  {
    "title": "Digital Marketing Expert",
    "issuer": "Indian Council for Technical Research and Developement",
    "image": "/assets/certificates/irctd.jpg",
    "link": "https://www.ictrd.org/TID/16965086",
    "issueDate": "24th February 2024"
  },
  {
    "title": "Crtical Bug",
    "issuer": "Apna Nivesh",
    "image": "/assets/certificates/apna_nives.jpg",
    "link": "https://drive.google.com/file/d/1mfxhxIm0rYsV71oRUNH1IOHVDIy0J_vO/view",
    "issueDate": "1st February 2024"
  },
  {
    "title": "Internshala Student Partner",
    "issuer": "Internshala",
    "image": "/assets/certificates/internshala.jpg",
    "link": "https://drive.google.com/file/d/1rK6DKEid41Rm3rlvs-NnXph_W8r4QCyN/view",
    "issueDate": "1st January 2024"
  },
  {
    "title": "Poster Competition",
    "issuer": "Charusat University",
    "image": "/assets/certificates/poster_competition.png",
    "link": "https://drive.google.com/file/d/1eQUIEP4pMk7vQp600YAbZ2QXRHRgPSuv/view",
    "issueDate": "Apr 2024"
  },
  {
    "title": "Digital Marketing Course",
    "issuer": "Charusat University",
    "image": "/assets/certificates/dm_charusat.jpg",
    "link": "https://drive.google.com/file/d/1jCH9QA96Pz4CQQrdyv1t_kQI_Ayk4i_W/view",
    "issueDate": "1st November 2023"
    },
  {
    "title": "Short Term Training Program",
    "issuer": "Charusat University",
    "image": "/assets/certificates/sttp.jpg",
    "link": "https://drive.google.com/file/d/14nfXY1W02KD5W0P3eDbSmx1VBIpDQVME/view",
    "issueDate": "Apr 2024"
    },
  {
    "title": "Cyber Security And Privacy",
    "issuer": "NPTEL",
    "image": "/assets/certificates/nptel.jpg",
    "link": "https://archive.nptel.ac.in/content/noc/NOC23/SEM2/Ecertificates/106/noc23-cs127/Course/NPTEL23CS127S53110022220274476.pdf",
    "issueDate": "16th October 2023"
  },
  {
    "title": "Galactic Problem Solver",
    "issuer": "NASA Space Apps",
    "image": "/assets/certificates/galactic.jpg",
    "link": "https://drive.google.com/file/d/1IVW7i4gbvB5Y-JDHGVIL6SNSi1H_fD3R/view",
    "issueDate": "10th October 2023"
    },
  {
    "title": "Introduction to MongoDB",
    "issuer": "MongoDB University",
    "image": "/assets/certificates/mongo.jpg",
    "link": "https://drive.google.com/file/d/19pHJtGy9xMrF-e6rGrsJb1zyBj3wTOpp/view",
    "issueDate": "19th September 2023"
  }
]
